download.py
sikumim-0.1.5.dist-info/LICENSE
sikumim-0.1.5.dist-info/METADATA
sikumim-0.1.5.dist-info/WHEEL
sikumim-0.1.5.dist-info/entry_points.txt
sikumim-0.1.5.dist-info/top_level.txt
sikumim-0.1.5.dist-info/RECORD
