Metadata-Version: 2.2
Name: sikumim
Version: 0.1.5
Summary: A simple tool to download lecture notes, written by Regev Yehezkel Imra
Author: Eitan Sztuden
Classifier: Programming Language :: Python :: 3
Classifier: License :: OSI Approved :: MIT License
Classifier: Operating System :: OS Independent
License-File: LICENSE
Requires-Dist: requests
Dynamic: author
Dynamic: classifier
Dynamic: description
Dynamic: description-content-type
Dynamic: requires-dist
Dynamic: summary
